Metadata-Version: 1.1
Name: cfcal
Version: 0.1.5
Summary: Python calculator for crystal fields
Home-page: http://github.com/rayosborn/cfcal
Author: Ray Osborn
Author-email: rayosborn@mac.com
License: BSD
Keywords: rare earth crystal fields
Platform: UNKNOWN
Classifier: Development Status :: 4 - Beta
Classifier: Topic :: Scientific/Engineering
Classifier: License :: OSI Approved :: BSD License
Classifier: Programming Language :: Python :: 2.7
Classifier: Programming Language :: Python :: 3.5
Classifier: Programming Language :: Python :: 3.6
Requires: scipy
Requires: numpy
